ipysplitpanes/__init__.py
ipysplitpanes/_version.py
ipysplitpanes/widget.py
ipysplitpanes/labextension/package.json
ipysplitpanes/labextension/static/190.8fdf03a62bc0076d732d.js
ipysplitpanes/labextension/static/261.2bf7004fe626d0b5b457.js
ipysplitpanes/labextension/static/884.a62d64e51d920f851bc6.js
ipysplitpanes/labextension/static/remoteEntry.ef52ea88d0ec7b9b3b66.js
ipysplitpanes/labextension/static/style.js
ipysplitpanes/nbextension/extension.js
ipysplitpanes/nbextension/index.js
ipysplitpanes/nbextension/index.js.map
ipysplitpanes-0.2.0.data/data/etc/jupyter/nbconfig/notebook.d/jupyter-splitpanes.json
ipysplitpanes-0.2.0.data/data/share/jupyter/labextensions/jupyter-splitpanes/package.json
ipysplitpanes-0.2.0.data/data/share/jupyter/labextensions/jupyter-splitpanes/static/190.8fdf03a62bc0076d732d.js
ipysplitpanes-0.2.0.data/data/share/jupyter/labextensions/jupyter-splitpanes/static/261.2bf7004fe626d0b5b457.js
ipysplitpanes-0.2.0.data/data/share/jupyter/labextensions/jupyter-splitpanes/static/884.a62d64e51d920f851bc6.js
ipysplitpanes-0.2.0.data/data/share/jupyter/labextensions/jupyter-splitpanes/static/remoteEntry.ef52ea88d0ec7b9b3b66.js
ipysplitpanes-0.2.0.data/data/share/jupyter/labextensions/jupyter-splitpanes/static/style.js
ipysplitpanes-0.2.0.data/data/share/jupyter/nbextensions/jupyter-splitpanes/extension.js
ipysplitpanes-0.2.0.data/data/share/jupyter/nbextensions/jupyter-splitpanes/index.js
ipysplitpanes-0.2.0.data/data/share/jupyter/nbextensions/jupyter-splitpanes/index.js.map
ipysplitpanes-0.2.0.dist-info/METADATA
ipysplitpanes-0.2.0.dist-info/WHEEL
ipysplitpanes-0.2.0.dist-info/top_level.txt
ipysplitpanes-0.2.0.dist-info/RECORD
